bregmanet/__init__.py
bregmanet/mlp.py
bregmanet/resnet_large.py
bregmanet/resnet_small.py
bregmanet/utils/__init__.py
bregmanet/utils/activation.py
bregmanet/utils/weight.py
bregmanet-0.1.1.dist-info/LICENSE
bregmanet-0.1.1.dist-info/METADATA
bregmanet-0.1.1.dist-info/WHEEL
bregmanet-0.1.1.dist-info/top_level.txt
bregmanet-0.1.1.dist-info/RECORD
