Metadata-Version: 2.1
Name: bregmanet
Version: 0.1.1
Summary: Bregman Neural Networks
Home-page: https://github.com/JordanFrecon/bregmanet
Author: Jordan Frecon
Author-email: jordan.frecon@gmail.com
License: MIT
Requires-Python: >=3.6
License-File: LICENSE
